{
    "_documentation": "Blacklist works via SUBSTRING matching. Example: Adding 'onedrive' hides 'onedrive.exe', 'onedrive.sync.exe' and 'Microsoft OneDrive'. No wildcards needed.",
    "blacklistPatterns": [
        "host",
        "service",
        "system",
        "registry",
        "logon",
        "helper",
        "agent",
        "daemon",
        "runtime",
        "broker",
        "indexer",
        "search",
        "updater",
        "install",
        "setup",
        "nvidia",
        "amd",
        "intel",
        "driver",
        "audio",
        "sound",
        "peripherals",
        "mouse",
        "keyboard",
        "printer",
        "spooler",
        "synapse",
        "corsair",
        "ghub",
        "armoury",
        "background",
        "rendering",
        "crashpad",
        "monitor",
        "launcher",
        "client",
        "overlay",
        "steamwebhelper",
        "discordptb",
        "discordcanary",
        "msedgewebview2",
        "powershell",
        "pwsh",
        "cmd",
        "conhost",
        "winstore",
        "smartscreen",
        "securityhealth",
        "musnotify",
        "skypeapp",
        "onedrive",
        "winlogon",
        "csrss",
        "mmc",
        "ctfmon",
        "lockapp",
        "filecoauth",
        "explorer",
        "microsoft.photos",
        "searchapp",
        "startmenuexperiencehost",
        "taskmgr",
        "python",
        "vmware"
    ],
    "whitelist": {
        "games": [
            "minecraft",
            "javaw",
            "java",
            "bedrock",
            "roblox",
            "robloxplayerbeta",
            "fortnite",
            "fortniteclient",
            "steam",
            "gta5",
            "gtav",
            "valorant",
            "riotclient",
            "leagueclient",
            "league of legends",
            "csgo",
            "cs2",
            "dota2",
            "worldofwarcraft",
            "wow",
            "overwatch",
            "apex",
            "r5apex",
            "epicgameslauncher",
            "battlenet",
            "unity",
            "godot"
        ],
        "browsers": [
            "chrome",
            "msedge",
            "firefox",
            "opera",
            "brave",
            "vivaldi",
            "iexplore"
        ],
        "social": [
            "discord",
            "teams",
            "skype",
            "telegram",
            "whatsapp",
            "messenger",
            "signal",
            "slack",
            "zoom"
        ],
        "productivity": [
            "code",
            "cursor",
            "visual studio",
            "devenv",
            "idea",
            "pycharm",
            "webstorm",
            "word",
            "excel",
            "powerpoint",
            "outlook",
            "onenote",
            "notepad",
            "notepad++",
            "calculator",
            "mspaint",
            "photoshop",
            "illustrator",
            "premiere"
        ],
        "multimedia": [
            "spotify",
            "vlc",
            "mpv",
            "windows media player",
            "photos",
            "movies"
        ]
    },
    "friendlyNames": {
        "javaw": "Minecraft (Java)",
        "java": "Minecraft (Java)",
        "minecraft.windows": "Minecraft (Bedrock)",
        "robloxplayerbeta": "Roblox",
        "chrome": "Google Chrome",
        "msedge": "Microsoft Edge",
        "firefox": "Mozilla Firefox",
        "code": "VS Code",
        "cursor": "Cursor IDE",
        "devenv": "Visual Studio",
        "idea64": "IntelliJ IDEA",
        "steam": "Steam",
        "discord": "Discord",
        "spotify": "Spotify",
        "winword": "Microsoft Word",
        "excel": "Microsoft Excel",
        "powerpnt": "Microsoft PowerPoint",
        "r5apex": "Apex Legends",
        "cs2": "Counter-Strike 2",
        "valorant-win64-shipping": "Valorant"
    },
    "iconMapping": {
        "games": "game",
        "browsers": "globe",
        "social": "social",
        "productivity": "document",
        "multimedia": "video",
        "system": "cpu"
    }
}